{
    "id": 5,
    "episodeId": 5,
    "title": "Health Promotion & Maintenance Part 2",
    "description": "Maternity: Antepartum, Intrapartum, Postpartum, Newborn Care",
    "questionCount": 35,
    "color": "from-pink-600 to-rose-800",
    "questions": [
        {
            "id": 1,
            "text": "A pregnant client at 10 weeks gestation reports nausea and vomiting. Which recommendation is most appropriate?",
            "options": [
                "Eat three large meals per day",
                "Eat small, frequent meals and avoid spicy foods",
                "Drink large amounts of fluids with meals",
                "Lie down immediately after eating"
            ],
            "correctAnswer": 1,
            "explanation": "Small, frequent meals help manage morning sickness. Avoiding spicy, fatty foods and separating liquids from solids can reduce nausea."
        },
        {
            "id": 2,
            "text": "A nurse is teaching a prenatal class about fetal development. At what gestational age can the fetal heartbeat typically be heard with a Doppler?",
            "options": [
                "6-8 weeks",
                "10-12 weeks",
                "16-18 weeks",
                "20-22 weeks"
            ],
            "correctAnswer": 1,
            "explanation": "Fetal heart tones can typically be detected with a Doppler device at 10-12 weeks gestation. Earlier detection may be possible with transvaginal ultrasound."
        },
        {
            "id": 3,
            "text": "A client at 28 weeks gestation has a positive glucose challenge test. What is the next step?",
            "options": [
                "Diagnose gestational diabetes immediately",
                "Schedule a 3-hour glucose tolerance test",
                "Start insulin therapy",
                "Restrict all carbohydrates"
            ],
            "correctAnswer": 1,
            "explanation": "A positive glucose challenge test requires confirmation with a 3-hour glucose tolerance test before diagnosing gestational diabetes."
        },
        {
            "id": 4,
            "text": "Which finding in a pregnant client at 32 weeks gestation requires immediate intervention?",
            "options": [
                "Mild ankle edema at end of day",
                "Frequent urination",
                "Severe headache with blurred vision",
                "Backache after standing"
            ],
            "correctAnswer": 2,
            "explanation": "Severe headache with visual changes indicates possible preeclampsia, requiring immediate assessment of blood pressure and other symptoms."
        },
        {
            "id": 5,
            "text": "A nurse is teaching about warning signs during pregnancy. Which symptom should be reported immediately?",
            "options": [
                "Increased vaginal discharge",
                "Braxton Hicks contractions",
                "Sudden gush of fluid from vagina",
                "Mild constipation"
            ],
            "correctAnswer": 2,
            "explanation": "Sudden gush of fluid suggests rupture of membranes, requiring immediate evaluation to assess for infection risk and fetal well-being."
        },
        {
            "id": 6,
            "text": "What is the recommended weight gain during pregnancy for a woman with normal pre-pregnancy BMI?",
            "options": [
                "15-20 pounds",
                "25-35 pounds",
                "40-50 pounds",
                "10-15 pounds"
            ],
            "correctAnswer": 1,
            "explanation": "For women with normal BMI (18.5-24.9), the recommended weight gain is 25-35 pounds during pregnancy."
        },
        {
            "id": 7,
            "text": "A laboring client's membranes rupture spontaneously. What is the nurse's priority action?",
            "options": [
                "Document the time and characteristics",
                "Assess fetal heart rate",
                "Notify the provider",
                "Prepare for delivery"
            ],
            "correctAnswer": 1,
            "explanation": "After rupture of membranes, immediately assess fetal heart rate to detect cord prolapse or compression, which can cause fetal distress."
        },
        {
            "id": 8,
            "text": "A client in active labor has contractions every 3 minutes lasting 60 seconds. The cervix is dilated 6 cm. What stage of labor is this?",
            "options": [
                "First stage, latent phase",
                "First stage, active phase",
                "Second stage",
                "Third stage"
            ],
            "correctAnswer": 1,
            "explanation": "Active phase of first stage labor is characterized by cervical dilation of 4-7 cm with regular, strong contractions."
        },
        {
            "id": 9,
            "text": "Which fetal heart rate pattern requires immediate intervention?",
            "options": [
                "Baseline 140 bpm with moderate variability",
                "Early decelerations with contractions",
                "Late decelerations with each contraction",
                "Accelerations with fetal movement"
            ],
            "correctAnswer": 2,
            "explanation": "Late decelerations indicate uteroplacental insufficiency and fetal hypoxia, requiring immediate intervention (position change, oxygen, IV fluids)."
        },
        {
            "id": 10,
            "text": "A client receives an epidural for labor pain. What is the priority nursing assessment?",
            "options": [
                "Level of consciousness",
                "Blood pressure",
                "Respiratory rate",
                "Temperature"
            ],
            "correctAnswer": 1,
            "explanation": "Hypotension is a common side effect of epidural anesthesia due to vasodilation. Monitor blood pressure frequently and position client on left side."
        },
        {
            "id": 11,
            "text": "Which finding indicates the transition phase of labor?",
            "options": [
                "Cervix dilated 3 cm",
                "Contractions every 10 minutes",
                "Cervix dilated 8-10 cm with intense contractions",
                "Delivery of the placenta"
            ],
            "correctAnswer": 2,
            "explanation": "Transition phase occurs at 8-10 cm dilation with very strong, frequent contractions. Client may feel overwhelmed and irritable."
        },
        {
            "id": 12,
            "text": "A client is pushing during second stage of labor. Which position is most effective?",
            "options": [
                "Supine with legs in stirrups",
                "Squatting or semi-sitting",
                "Prone position",
                "Trendelenburg position"
            ],
            "correctAnswer": 1,
            "explanation": "Upright positions (squatting, semi-sitting) use gravity to assist descent and allow pelvic diameter to increase, facilitating delivery."
        },
        {
            "id": 13,
            "text": "When should the nurse expect delivery of the placenta after birth?",
            "options": [
                "Immediately after birth",
                "Within 5-30 minutes",
                "Within 1-2 hours",
                "Within 24 hours"
            ],
            "correctAnswer": 1,
            "explanation": "The third stage of labor (placental delivery) typically occurs within 5-30 minutes after birth. Prolonged third stage increases hemorrhage risk."
        },
        {
            "id": 14,
            "text": "A postpartum client has a boggy uterus. What is the first nursing action?",
            "options": [
                "Notify the provider",
                "Massage the fundus",
                "Administer oxytocin",
                "Check for bladder distention"
            ],
            "correctAnswer": 1,
            "explanation": "A boggy (soft, uncontracted) uterus indicates uterine atony. First action is to massage the fundus to stimulate contraction and prevent hemorrhage."
        },
        {
            "id": 15,
            "text": "What is the expected location of the fundus immediately after delivery?",
            "options": [
                "At the umbilicus",
                "2 cm above the umbilicus",
                "Below the umbilicus",
                "At the symphysis pubis"
            ],
            "correctAnswer": 0,
            "explanation": "Immediately postpartum, the fundus should be firm and at or slightly below the umbilicus. It descends approximately 1 cm per day."
        },
        {
            "id": 16,
            "text": "A breastfeeding mother asks about afterpains. What should the nurse explain?",
            "options": [
                "They indicate infection",
                "They are caused by oxytocin release during breastfeeding",
                "They should not occur after the first birth",
                "They require pain medication"
            ],
            "correctAnswer": 1,
            "explanation": "Afterpains are uterine contractions caused by oxytocin release during breastfeeding. They are more common in multiparas and help prevent hemorrhage."
        },
        {
            "id": 17,
            "text": "Which lochia characteristic on postpartum day 1 is normal?",
            "options": [
                "Lochia alba (white/yellow)",
                "Lochia rubra (red) with small clots",
                "Lochia serosa (pink/brown)",
                "No lochia present"
            ],
            "correctAnswer": 1,
            "explanation": "Lochia rubra (red, bloody discharge) with small clots is normal for days 1-3 postpartum. Large clots or excessive bleeding require assessment."
        },
        {
            "id": 18,
            "text": "A postpartum client reports severe perineal pain. What should the nurse assess first?",
            "options": [
                "Vital signs",
                "Perineum for hematoma",
                "Fundal height",
                "Lochia amount"
            ],
            "correctAnswer": 1,
            "explanation": "Severe perineal pain may indicate hematoma formation. Assess for swelling, discoloration, and asymmetry of the perineum."
        },
        {
            "id": 19,
            "text": "What is the priority teaching for a client with postpartum preeclampsia?",
            "options": [
                "Increase fluid intake",
                "Report headache or visual changes immediately",
                "Limit visitors",
                "Avoid breastfeeding"
            ],
            "correctAnswer": 1,
            "explanation": "Postpartum preeclampsia can progress to eclampsia (seizures). Teach client to report warning signs: severe headache, visual changes, epigastric pain."
        },
        {
            "id": 20,
            "text": "When should a postpartum client resume sexual activity?",
            "options": [
                "After 1 week",
                "After 2 weeks",
                "After lochia stops and perineum heals (4-6 weeks)",
                "After 3 months"
            ],
            "correctAnswer": 2,
            "explanation": "Sexual activity should be delayed until lochia has stopped and perineal healing is complete, typically 4-6 weeks postpartum."
        },
        {
            "id": 21,
            "text": "A newborn's Apgar score at 1 minute is 8. What does this indicate?",
            "options": [
                "Severe distress requiring resuscitation",
                "Moderate distress",
                "Good condition with minimal intervention needed",
                "Perfect condition"
            ],
            "correctAnswer": 2,
            "explanation": "Apgar scores: 7-10 = good condition, 4-6 = moderate distress, 0-3 = severe distress. Score of 8 indicates good adaptation to extrauterine life."
        },
        {
            "id": 22,
            "text": "What is the normal respiratory rate for a newborn?",
            "options": [
                "20-30 breaths/minute",
                "30-60 breaths/minute",
                "60-80 breaths/minute",
                "10-20 breaths/minute"
            ],
            "correctAnswer": 1,
            "explanation": "Normal newborn respiratory rate is 30-60 breaths per minute. Rates above 60 may indicate respiratory distress."
        },
        {
            "id": 23,
            "text": "A newborn has a heart rate of 180 bpm while crying. What should the nurse do?",
            "options": [
                "Call the provider immediately",
                "Reassess when baby is calm",
                "Administer oxygen",
                "Prepare for resuscitation"
            ],
            "correctAnswer": 1,
            "explanation": "Normal newborn heart rate is 120-160 bpm at rest, but can increase to 180 bpm when crying. Reassess when calm to determine true baseline."
        },
        {
            "id": 24,
            "text": "What is the purpose of administering vitamin K to a newborn?",
            "options": [
                "Prevent infection",
                "Prevent bleeding",
                "Promote bonding",
                "Stimulate breathing"
            ],
            "correctAnswer": 1,
            "explanation": "Vitamin K is given IM to prevent hemorrhagic disease of the newborn. Newborns have sterile intestines and cannot produce vitamin K initially."
        },
        {
            "id": 25,
            "text": "Erythromycin eye ointment is administered to newborns to prevent which infection?",
            "options": [
                "Conjunctivitis from gonorrhea and chlamydia",
                "Respiratory infections",
                "Skin infections",
                "Umbilical cord infections"
            ],
            "correctAnswer": 0,
            "explanation": "Erythromycin eye ointment prevents ophthalmia neonatorum (eye infection) caused by gonorrhea or chlamydia transmitted during vaginal delivery."
        },
        {
            "id": 26,
            "text": "A newborn's axillary temperature is 97.2°F (36.2°C). What is the priority action?",
            "options": [
                "Document as normal",
                "Place under radiant warmer and reassess",
                "Give a warm bath",
                "Administer antibiotics"
            ],
            "correctAnswer": 1,
            "explanation": "Normal newborn temperature is 97.7-99.5°F (36.5-37.5°C). Temperature of 97.2°F indicates hypothermia requiring warming and reassessment."
        },
        {
            "id": 27,
            "text": "What is the best way to assess for adequate breastfeeding in a newborn?",
            "options": [
                "Baby sleeps 6 hours between feedings",
                "6-8 wet diapers and 3-4 stools per day by day 4",
                "Baby feeds every 4 hours",
                "Baby gains 1 pound per week"
            ],
            "correctAnswer": 1,
            "explanation": "Adequate hydration and nutrition are indicated by 6-8 wet diapers and 3-4 stools daily by day 4. Newborns should feed 8-12 times per 24 hours."
        },
        {
            "id": 28,
            "text": "A newborn develops jaundice on day 2 of life. What is the most likely cause?",
            "options": [
                "Liver disease",
                "Physiologic jaundice from RBC breakdown",
                "Infection",
                "Biliary atresia"
            ],
            "correctAnswer": 1,
            "explanation": "Physiologic jaundice appears after 24 hours due to normal RBC breakdown and immature liver. Jaundice before 24 hours is pathologic and requires investigation."
        },
        {
            "id": 29,
            "text": "What is the correct technique for umbilical cord care?",
            "options": [
                "Apply antibiotic ointment daily",
                "Keep clean and dry, fold diaper below cord",
                "Cover with petroleum jelly",
                "Submerge in water during baths"
            ],
            "correctAnswer": 1,
            "explanation": "Keep cord clean and dry. Fold diaper below cord to prevent urine contamination. Cord typically falls off in 10-14 days."
        },
        {
            "id": 30,
            "text": "A mother asks when to call the provider about her newborn. Which symptom requires immediate attention?",
            "options": [
                "Sneezing occasionally",
                "Sleeping 16 hours per day",
                "Temperature of 100.4°F (38°C) or higher",
                "Hiccups after feeding"
            ],
            "correctAnswer": 2,
            "explanation": "Fever (≥100.4°F/38°C) in a newborn may indicate serious infection and requires immediate medical evaluation."
        },
        {
            "id": 31,
            "text": "What is the recommended sleep position for newborns to reduce SIDS risk?",
            "options": [
                "Prone (on stomach)",
                "Side-lying",
                "Supine (on back)",
                "Semi-upright in car seat"
            ],
            "correctAnswer": 2,
            "explanation": "Back to sleep (supine position) significantly reduces SIDS risk. Avoid soft bedding, pillows, and bed-sharing."
        },
        {
            "id": 32,
            "text": "A breastfeeding mother reports sore, cracked nipples. What is the best advice?",
            "options": [
                "Stop breastfeeding immediately",
                "Check baby's latch and positioning",
                "Apply soap to nipples",
                "Limit feeding to 5 minutes per breast"
            ],
            "correctAnswer": 1,
            "explanation": "Sore nipples usually result from poor latch. Assess positioning and ensure baby takes entire areola into mouth, not just the nipple."
        },
        {
            "id": 33,
            "text": "When should a newborn have the first bowel movement (meconium)?",
            "options": [
                "Within 24-48 hours after birth",
                "Within 1 week",
                "Immediately after birth",
                "Within 72 hours"
            ],
            "correctAnswer": 0,
            "explanation": "Meconium (first stool) should be passed within 24-48 hours. Failure to pass meconium may indicate intestinal obstruction or other problems."
        },
        {
            "id": 34,
            "text": "What is the normal newborn blood glucose level?",
            "options": [
                "20-40 mg/dL",
                "40-60 mg/dL",
                "60-100 mg/dL",
                "100-120 mg/dL"
            ],
            "correctAnswer": 1,
            "explanation": "Normal newborn glucose is 40-60 mg/dL in first hours, then 60-100 mg/dL. Levels <40 mg/dL indicate hypoglycemia requiring intervention."
        },
        {
            "id": 35,
            "text": "A mother asks about circumcision care. What should the nurse teach?",
            "options": [
                "Remove the yellow exudate immediately",
                "Apply petroleum jelly with each diaper change",
                "Avoid diaper changes for 24 hours",
                "Submerge in bath water immediately"
            ],
            "correctAnswer": 1,
            "explanation": "Apply petroleum jelly to prevent diaper from sticking to healing site. Yellow exudate is normal granulation tissue. Avoid tub baths until healed."
        }
    ]
}